anchor_mcp_sentry/__init__.py
anchor_mcp_sentry/__main__.py
anchor_mcp_sentry/server.py
anchor_mcp_sentry-0.6.2.dist-info/METADATA
anchor_mcp_sentry-0.6.2.dist-info/WHEEL
anchor_mcp_sentry-0.6.2.dist-info/entry_points.txt
anchor_mcp_sentry-0.6.2.dist-info/RECORD
